{
  "packages": [
    {
      "pkg":"com.ss.android.ugc.aweme",
      "actionConfigs":[
        {
          "keyCode":700,
          "version":"",
          "startActivity":"com.ss.android.ugc.aweme.main.MainActivity",
          "flagAction":4,
          "flagResult":1,
          "flagCondition":0,
          "condition":true,
          "viewID":"",
          "viewClassName":"",
          "touchEvent":"541,2169,541,2267,0",
          "targetActivity":"com.ss.android.ugc.aweme.shortvideo.ui.VideoRecordPermissionActivity"
        },
        {
          "keyCode":700,
          "version":"",
          "startActivity":"com.ss.android.ugc.aweme.shortvideo.ui.VideoRecordNewActivity",
          "flagAction":4,
          "flagResult":1,
          "flagCondition":3,
          "condition":true,
          "viewID":"",
          "viewClassName":"",
          "touchEvent":"981,120,981,120,0",
          "targetActivity":""
        },
        {
          "keyCode":701,
          "version":"",
          "startActivity":"com.ss.android.ugc.aweme.shortvideo.ui.VideoRecordNewActivity",
          "flagAction":8,
          "flagResult":0,
          "flagCondition":5,
          "condition":true,
          "viewID":"",
          "viewClassName":"",
          "touchEvent":"",
          "targetActivity":""
        }
      ]
    },
    {
      "pkg":"com.ss.android.ugc.live",
      "actionConfigs":[
        {
          "keyCode":700,
          "version":"",
          "startActivity":"com.ss.android.ugc.live.main.MainActivity",
          "flagAction":4,
          "flagResult":1,
          "flagCondition":0,
          "condition":true,
          "viewID":"",
          "viewClassName":"",
          "touchEvent":"541,2146,541,2274,0",
          "targetActivity":""
        },
        {
          "keyCode":700,
          "version":"",
          "startActivity":"com.ss.android.ugc.live.shortvideo.ui.VideoRecordActivity",
          "flagAction":4,
          "flagResult":1,
          "flagCondition":3,
          "condition":true,
          "viewID":"",
          "viewClassName":"",
          "touchEvent":"856,77,856,77,0",
          "targetActivity":""
        },
        {
          "keyCode":701,
          "version":"",
          "startActivity":"com.ss.android.ugc.live.shortvideo.ui.VideoRecordActivity",
          "flagAction":1,
          "flagResult":0,
          "flagCondition":1,
          "condition":true,
          "viewID":"closelive",
          "viewClassName":"",
          "touchEvent":"",
          "targetActivity":""
        }
      ]
    },
    {
      "pkg":"com.tencent.ttpic",
      "actionConfigs":[
        {
          "keyCode":700,
          "version":"",
          "startActivity":"com.tencent.ttpic.module.MainActivity",
          "flagAction":4,
          "flagResult":1,
          "flagCondition":0,
          "condition":true,
          "viewID":"btn_camera",
          "viewClassName":"",
          "touchEvent":"541,2034,541,2158,0",
          "targetActivity":""
        },
        {
          "keyCode":700,
          "version":"",
          "startActivity":"com.tencent.ttpic.module.camera.CameraActivity",
          "flagAction":1,
          "flagResult":1,
          "flagCondition":3,
          "condition":true,
          "viewID":"btn_switch",
          "viewClassName":"",
          "touchEvent":"1010,82,1010,82,0",
          "targetActivity":""
        },
        {
          "keyCode":701,
          "version":"",
          "startActivity":"com.tencent.ttpic.module.camera.CameraActivity",
          "flagAction":8,
          "flagResult":0,
          "flagCondition":5,
          "condition":true,
          "viewID":"",
          "viewClassName":"",
          "touchEvent":"",
          "targetActivity":""
        }
      ]
    },
    {
      "pkg":"com.mt.mtxx.mtxx",
      "actionConfigs":[
        {
          "keyCode":700,
          "version":"",
          "startActivity":"com.meitu.mtxx.MainActivity",
          "flagAction":4,
          "flagResult":1,
          "flagCondition":0,
          "condition":true,
          "viewID":"",
          "viewClassName":"",
          "touchEvent":"541,2065,541,2200,0",
          "targetActivity":""
        },
        {
          "keyCode":700,
          "version":"",
          "startActivity":"com.meitu.app.meitucamera.ActivityCamera",
          "flagAction":4,
          "flagResult":1,
          "flagCondition":3,
          "condition":true,
          "viewID":"",
          "viewClassName":"",
          "touchEvent":"862,149,862,149,0",
          "targetActivity":""
        },
        {
          "keyCode":701,
          "version":"",
          "startActivity":"com.meitu.app.meitucamera.ActivityCamera",
          "flagAction":1,
          "flagResult":1,
          "flagCondition":0,
          "condition":true,
          "viewID":"close_btn",
          "viewClassName":"",
          "touchEvent":"70,180,70,180,0",
          "targetActivity":""
        }
      ]
    },
    {
      "pkg":"com.tencent.mm",
      "actionConfigs":[
        {
          "keyCode":700,
          "version":"",
          "startActivity":"com.tencent.mm.plugin.voip.ui.VideoActivity",
          "flagAction":4,
          "flagResult":0,
          "flagCondition":4,
          "condition":false,
          "viewID":"",
          "viewClassName":"",
          "touchEvent":"874,1991,885,2130,0",
          "targetActivity":""
        }
      ]
    },
    {
      "pkg":"com.tencent.mobileqq",
      "actionConfigs":[
        {
          "keyCode":700,
          "version":"",
          "startActivity":"com.tencent.av.ui.VideoInviteFull",
          "flagAction":4,
          "flagResult":0,
          "flagCondition":4,
          "condition":false,
          "viewID":"",
          "viewClassName":"",
          "touchEvent":"750,2075,750,2195,0",
          "targetActivity":""
        }
      ]
    },
    {
      "pkg":"com.commsource.beautyplus",
      "actionConfigs":[
        {
          "keyCode":700,
          "version":"",
          "startActivity":"com.commsource.beautyplus.HomeActivity",
          "flagAction":1,
          "flagResult":1,
          "flagCondition":0,
          "condition":true,
          "viewID":"rl_home_btn_camera",
          "viewClassName":"",
          "touchEvent":"",
          "targetActivity":""
        },
        {
          "keyCode":700,
          "version":"",
          "startActivity":"com.commsource.camera.CameraActvity",
          "flagAction":1,
          "flagResult":1,
          "flagCondition":3,
          "condition":true,
          "viewID":"iv_switch_camera",
          "viewClassName":"",
          "touchEvent":"",
          "targetActivity":""
        },
        {
          "keyCode":700,
          "version":"",
          "startActivity":"com.commsource.video.RecordVideoActivity",
          "flagAction":4,
          "flagResult":1,
          "flagCondition":3,
          "condition":true,
          "viewID":"",
          "viewClassName":"",
          "touchEvent":"1000,60,1000,60,0",
          "targetActivity":""
        },
        {
          "keyCode":701,
          "version":"",
          "startActivity":"com.commsource.camera.CameraActvity",
          "flagAction":8,
          "flagResult":0,
          "flagCondition":5,
          "condition":true,
          "viewID":"",
          "viewClassName":"",
          "touchEvent":"",
          "targetActivity":""
        },
        {
          "keyCode":701,
          "version":"",
          "startActivity":"com.commsource.video.RecordVideoActivity",
          "flagAction":8,
          "flagResult":0,
          "flagCondition":5,
          "condition":true,
          "viewID":"",
          "viewClassName":"",
          "touchEvent":"",
          "targetActivity":""
        }
      ]
    },
    {
      "pkg":"com.cyberlink.youperfect",
      "actionConfigs":[
        {
          "keyCode":700,
          "version":"",
          "startActivity":"com.cyberlink.youperfect.activity.LauncherActivity",
          "flagAction":4,
          "flagResult":1,
          "flagCondition":0,
          "condition":true,
          "viewID":"SimpleCameraBtn",
          "viewClassName":"",
          "touchEvent":"320,1430,320,1564,0",
          "targetActivity":""
        },
        {
          "keyCode":700,
          "version":"",
          "startActivity":"com.cyberlink.youperfect.activity.PfCameraActivity",
          "flagAction":4,
          "flagResult":1,
          "flagCondition":3,
          "condition":true,
          "viewID":"SimpleCameraBtn",
          "viewClassName":"",
          "touchEvent":"1028,55,1028,55,0",
          "targetActivity":""
        },
        {
          "keyCode":701,
          "version":"",
          "startActivity":"com.cyberlink.youperfect.activity.PfCameraActivity",
          "flagAction":8,
          "flagResult":0,
          "flagCondition":5,
          "condition":true,
          "viewID":"",
          "viewClassName":"",
          "touchEvent":"",
          "targetActivity":""
        }
      ]
    },
    {
      "pkg":"com.meitu.meiyancamera",
      "actionConfigs":[
        {
          "keyCode":700,
          "version":"",
          "startActivity":"com.meitu.myxj.home.activity.HomeActivity",
          "flagAction":4,
          "flagResult":1,
          "flagCondition":0,
          "condition":true,
          "viewID":"",
          "viewClassName":"",
          "touchEvent":"536,1846,536,1903,0",
          "targetActivity":""
        },
        {
          "keyCode":700,
          "version":"",
          "startActivity":"com.meitu.myxj.selfie.merge.activity.SelfieCameraActivity",
          "flagAction":4,
          "flagResult":1,
          "flagCondition":3,
          "condition":true,
          "viewID":"",
          "viewClassName":"",
          "touchEvent":"1000,172,1000,172,0",
          "targetActivity":""
        },
        {
          "keyCode":701,
          "version":"",
          "startActivity":"com.meitu.myxj.selfie.merge.activity.SelfieCameraActivity",
          "flagAction":4,
          "flagResult":0,
          "flagCondition":1,
          "condition":true,
          "viewID":"",
          "viewClassName":"",
          "touchEvent":"73,188,73,188,0",
          "targetActivity":""
        }
      ]
    },
    {
      "pkg":"com.smile.gifmaker",
      "actionConfigs":[
        {
          "keyCode":700,
          "version":"",
          "startActivity":"com.yxcorp.gifshow.HomeActivity",
          "flagAction":4,
          "flagResult":1,
          "flagCondition":0,
          "condition":true,
          "viewID":"",
          "viewClassName":"",
          "touchEvent":"1012,174,1012,174,0",
          "targetActivity":""
        },
        {
          "keyCode":700,
          "version":"",
          "startActivity":"com.yxcorp.gifshow.camera.record.CameraActivity",
          "flagAction":4,
          "flagResult":1,
          "flagCondition":3,
          "condition":true,
          "viewID":"",
          "viewClassName":"",
          "touchEvent":"1000,78,1000,78,0",
          "targetActivity":""
        },
        {
          "keyCode":701,
          "version":"",
          "startActivity":"com.yxcorp.gifshow.camera.record.CameraActivity",
          "flagAction":1,
          "flagResult":1,
          "flagCondition":0,
          "condition":true,
          "viewID":"button_close",
          "viewClassName":"",
          "touchEvent":"",
          "targetActivity":""
        }
      ]
    },
    {
      "pkg":"com.meitu.meipaimv",
      "actionConfigs":[
        {
          "keyCode":700,
          "version":"",
          "startActivity":"com.meitu.meipaimv.community.main.MainActivity",
          "flagAction":4,
          "flagResult":1,
          "flagCondition":0,
          "condition":true,
          "viewID":"",
          "viewClassName":"",
          "touchEvent":"541,2130,541,2260,0",
          "targetActivity":""
        },
        {
          "keyCode":700,
          "version":"",
          "startActivity":"com.meitu.meipaimv.produce.camera.ui.CameraVideoActivity",
          "flagAction":4,
          "flagResult":1,
          "flagCondition":3,
          "condition":true,
          "viewID":"",
          "viewClassName":"",
          "touchEvent":"1023,160,1023,160,0",
          "targetActivity":""
        },
        {
          "keyCode":701,
          "version":"",
          "startActivity":"com.meitu.meipaimv.produce.camera.ui.CameraVideoActivity",
          "flagAction":8,
          "flagResult":0,
          "flagCondition":1,
          "condition":true,
          "viewID":"",
          "viewClassName":"",
          "touchEvent":"",
          "targetActivity":""
        }
      ]
    },
    {
      "pkg":"vStudio.Android.Camera360",
      "actionConfigs":[
        {
          "keyCode":700,
          "version":"",
          "startActivity":"com.pinguo.camera360.homepage.HomePageActivity",
          "flagAction":4,
          "flagResult":1,
          "flagCondition":0,
          "condition":true,
          "viewID":"",
          "viewClassName":"",
          "touchEvent":"541,2030,541,2160,0",
          "targetActivity":""
        },
        {
          "keyCode":700,
          "version":"",
          "startActivity":"vStudio.Android.Camera360.activity.CameraMainActivity",
          "flagAction":4,
          "flagResult":1,
          "flagCondition":3,
          "condition":true,
          "viewID":"",
          "viewClassName":"",
          "touchEvent":"1013,70,1013,70,0",
          "targetActivity":""
        },
        {
          "keyCode":701,
          "version":"",
          "startActivity":"vStudio.Android.Camera360.activity.CameraMainActivity",
          "flagAction":8,
          "flagResult":0,
          "flagCondition":5,
          "condition":true,
          "viewID":"",
          "viewClassName":"",
          "touchEvent":"",
          "targetActivity":""
        }
      ]
    },
    {
      "pkg":"com.campmobile.snowcamera",
      "actionConfigs":[
        {
          "keyCode":700,
          "version":"",
          "startActivity":"com.linecorp.b612.android.activity.ActivityCamera",
          "flagAction":4,
          "flagResult":1,
          "flagCondition":3,
          "condition":true,
          "viewID":"",
          "viewClassName":"",
          "touchEvent":"1002,75,1002,75,0",
          "targetActivity":""
        },
        {
          "keyCode":701,
          "version":"",
          "startActivity":"com.linecorp.b612.android.activity.ActivityCamera",
          "flagAction":8,
          "flagResult":1,
          "flagCondition":5,
          "condition":true,
          "viewID":"",
          "viewClassName":"",
          "touchEvent":"",
          "targetActivity":""
        }
      ]
    },
    {
      "pkg":"com.lemon.faceu",
      "actionConfigs":[
        {
          "keyCode":700,
          "version":"",
          "startActivity":"com.lemon.faceu.mainpage.MainActivity",
          "flagAction":4,
          "flagResult":1,
          "flagCondition":3,
          "condition":true,
          "viewID":"",
          "viewClassName":"",
          "touchEvent":"978,106,978,106,0",
          "targetActivity":""
        },
        {
          "keyCode":701,
          "version":"",
          "startActivity":"com.lemon.faceu.mainpage.MainActivity",
          "flagAction":8,
          "flagResult":1,
          "flagCondition":5,
          "condition":true,
          "viewID":"",
          "viewClassName":"",
          "touchEvent":"",
          "targetActivity":""
        }
      ]
    }
  ]
}
